Workbook

Sheet Raw Data
A1: Month | B1: Store | C1: SKU | D1: Product Name | E1: Category | F1: Unit Price | G1: Avg Daily Demand | H1: Days in Month | I1: Days Out of Stock | J1: Days In Stock | K1: Units Sold | L1: Lost Sales ($) | M1: Avg Inventory (units) | N1: Inventory Turns | O1: Tier
A2: 2026-01 | B2: Downtown | C2: KIT-101 | D2: Ceramic Nonstick Pan Set | E2: Kitchen | F2: 45 | G2: 14.2 | H2: 31 | I2: 4 | J2: =H2-I2 -> 27 | K2: =ROUND(G2*J2,0) -> 383 | L2: =ROUND(I2*G2*F2,2) -> 2556 | M2: 33.5 | N2: =IFERROR(ROUND(K2/M2,2),0) -> 11.43 | O2: fast
A3: 2026-02 | B3: Downtown | C3: KIT-101 | D3: Ceramic Nonstick Pan Set | E3: Kitchen | F3: 45 | G3: 11.4 | H3: 28 | I3: 6 | J3: =H3-I3 -> 22 | K3: =ROUND(G3*J3,0) -> 251 | L3: =ROUND(I3*G3*F3,2) -> 3078 | M3: 33.4 | N3: =IFERROR(ROUND(K3/M3,2),0) -> 7.51 | O3: fast
A4: 2026-03 | B4: Downtown | C4: KIT-101 | D4: Ceramic Nonstick Pan Set | E4: Kitchen | F4: 45 | G4: 14.5 | H4: 31 | I4: 12 | J4: =H4-I4 -> 19 | K4: =ROUND(G4*J4,0) -> 276 | L4: =ROUND(I4*G4*F4,2) -> 7830 | M4: 17.2 | N4: =IFERROR(ROUND(K4/M4,2),0) -> 16.05 | O4: fast
A5: 2026-04 | B5: Downtown | C5: KIT-101 | D5: Ceramic Nonstick Pan Set | E5: Kitchen | F5: 45 | G5: 12.6 | H5: 30 | I5: 4 | J5: =H5-I5 -> 26 | K5: =ROUND(G5*J5,0) -> 328 | L5: =ROUND(I5*G5*F5,2) -> 2268 | M5: 17.3 | N5: =IFERROR(ROUND(K5/M5,2),0) -> 18.96 | O5: fast
A6: 2026-05 | B6: Downtown | C6: KIT-101 | D6: Ceramic Nonstick Pan Set | E6: Kitchen | F6: 45 | G6: 11.3 | H6: 31 | I6: 4 | J6: =H6-I6 -> 27 | K6: =ROUND(G6*J6,0) -> 305 | L6: =ROUND(I6*G6*F6,2) -> 2034 | M6: 29 | N6: =IFERROR(ROUND(K6/M6,2),0) -> 10.52 | O6: fast
A7: 2026-06 | B7: Downtown | C7: KIT-101 | D7: Ceramic Nonstick Pan Set | E7: Kitchen | F7: 45 | G7: 14.8 | H7: 30 | I7: 12 | J7: =H7-I7 -> 18 | K7: =ROUND(G7*J7,0) -> 266 | L7: =ROUND(I7*G7*F7,2) -> 7992 | M7: 25.5 | N7: =IFERROR(ROUND(K7/M7,2),0) -> 10.43 | O7: fast
A8: 2026-01 | B8: Uptown | C8: KIT-101 | D8: Ceramic Nonstick Pan Set | E8: Kitchen | F8: 45 | G8: 10.7 | H8: 31 | I8: 8 | J8: =H8-I8 -> 23 | K8: =ROUND(G8*J8,0) -> 246 | L8: =ROUND(I8*G8*F8,2) -> 3852 | M8: 35.2 | N8: =IFERROR(ROUND(K8/M8,2),0) -> 6.99 | O8: fast
A9: 2026-02 | B9: Uptown | C9: KIT-101 | D9: Ceramic Nonstick Pan Set | E9: Kitchen | F9: 45 | G9: 8 | H9: 28 | I9: 6 | J9: =H9-I9 -> 22 | K9: =ROUND(G9*J9,0) -> 176 | L9: =ROUND(I9*G9*F9,2) -> 2160 | M9: 32.5 | N9: =IFERROR(ROUND(K9/M9,2),0) -> 5.42 | O9: fast
A10: 2026-03 | B10: Uptown | C10: KIT-101 | D10: Ceramic Nonstick Pan Set | E10: Kitchen | F10: 45 | G10: 10 | H10: 31 | I10: 6 | J10: =H10-I10 -> 25 | K10: =ROUND(G10*J10,0) -> 250 | L10: =ROUND(I10*G10*F10,2) -> 2700 | M10: 20.4 | N10: =IFERROR(ROUND(K10/M10,2),0) -> 12.25 | O10: fast
A11: 2026-04 | B11: Uptown | C11: KIT-101 | D11: Ceramic Nonstick Pan Set | E11: Kitchen | F11: 45 | G11: 12.6 | H11: 30 | I11: 5 | J11: =H11-I11 -> 25 | K11: =ROUND(G11*J11,0) -> 315 | L11: =ROUND(I11*G11*F11,2) -> 2835 | M11: 17.3 | N11: =IFERROR(ROUND(K11/M11,2),0) -> 18.21 | O11: fast
A12: 2026-05 | B12: Uptown | C12: KIT-101 | D12: Ceramic Nonstick Pan Set | E12: Kitchen | F12: 45 | G12: 8.6 | H12: 31 | I12: 9 | J12: =H12-I12 -> 22 | K12: =ROUND(G12*J12,0) -> 189 | L12: =ROUND(I12*G12*F12,2) -> 3483 | M12: 30.1 | N12: =IFERROR(ROUND(K12/M12,2),0) -> 6.28 | O12: fast
A13: 2026-06 | B13: Uptown | C13: KIT-101 | D13: Ceramic Nonstick Pan Set | E13: Kitchen | F13: 45 | G13: 12.8 | H13: 30 | I13: 11 | J13: =H13-I13 -> 19 | K13: =ROUND(G13*J13,0) -> 243 | L13: =ROUND(I13*G13*F13,2) -> 6336 | M13: 28.4 | N13: =IFERROR(ROUND(K13/M13,2),0) -> 8.56 | O13: fast
... A241: 2026-06 | B241: Riverside | C241: OUT-502 | D241: Garden Planter Pot | E241: Outdoor | F241: 15 | G241: 3.1 | H241: 30 | I241: 2 | J241: =H241-I241 -> 28 | K241: =ROUND(G241*J241,0) -> 87 | L241: =ROUND(I241*G241*F241,2) -> 93 | M241: 78.1 | N241: =IFERROR(ROUND(K241/M241,2),0) -> 1.11 | O241: slow

Sheet Category Summary
A1: Category | B1: Total Lost Sales ($) | C1: Total Units Sold | D1: Avg Stockout Days/Month | E1: Avg Inventory Turns
A2: Bedding | B2: =SUMIF('Raw Data'!$E$2:$E$241,A2,'Raw Data'!$L$2:$L$241) -> 124443 | C2: =SUMIF('Raw Data'!$E$2:$E$241,A2,'Raw Data'!$K$2:$K$241) -> 8218 | D2: =ROUND(AVERAGEIF('Raw Data'!$E$2:$E$241,A2,'Raw Data'!$I$2:$I$241),1) -> 4.5 | E2: =ROUND(AVERAGEIF('Raw Data'!$E$2:$E$241,A2,'Raw Data'!$N$2:$N$241),2) -> 5.42
A3: Outdoor | B3: =SUMIF('Raw Data'!$E$2:$E$241,A3,'Raw Data'!$L$2:$L$241) -> 109331 | C3: =SUMIF('Raw Data'!$E$2:$E$241,A3,'Raw Data'!$K$2:$K$241) -> 8070 | D3: =ROUND(AVERAGEIF('Raw Data'!$E$2:$E$241,A3,'Raw Data'!$I$2:$I$241),1) -> 4.4 | E3: =ROUND(AVERAGEIF('Raw Data'!$E$2:$E$241,A3,'Raw Data'!$N$2:$N$241),2) -> 5.4
A4: Kitchen | B4: =SUMIF('Raw Data'!$E$2:$E$241,A4,'Raw Data'!$L$2:$L$241) -> 88360.5 | C4: =SUMIF('Raw Data'!$E$2:$E$241,A4,'Raw Data'!$K$2:$K$241) -> 8215 | D4: =ROUND(AVERAGEIF('Raw Data'!$E$2:$E$241,A4,'Raw Data'!$I$2:$I$241),1) -> 4.3 | E4: =ROUND(AVERAGEIF('Raw Data'!$E$2:$E$241,A4,'Raw Data'!$N$2:$N$241),2) -> 5.52
A5: Decor | B5: =SUMIF('Raw Data'!$E$2:$E$241,A5,'Raw Data'!$L$2:$L$241) -> 67755.8 | C5: =SUMIF('Raw Data'!$E$2:$E$241,A5,'Raw Data'!$K$2:$K$241) -> 7771 | D5: =ROUND(AVERAGEIF('Raw Data'!$E$2:$E$241,A5,'Raw Data'!$I$2:$I$241),1) -> 5 | E5: =ROUND(AVERAGEIF('Raw Data'!$E$2:$E$241,A5,'Raw Data'!$N$2:$N$241),2) -> 4.76
A6: Storage | B6: =SUMIF('Raw Data'!$E$2:$E$241,A6,'Raw Data'!$L$2:$L$241) -> 53679 | C6: =SUMIF('Raw Data'!$E$2:$E$241,A6,'Raw Data'!$K$2:$K$241) -> 8309 | D6: =ROUND(AVERAGEIF('Raw Data'!$E$2:$E$241,A6,'Raw Data'!$I$2:$I$241),1) -> 4.5 | E6: =ROUND(AVERAGEIF('Raw Data'!$E$2:$E$241,A6,'Raw Data'!$N$2:$N$241),2) -> 5.4

Sheet SKU Summary
A1: SKU | B1: Product Name | C1: Category | D1: Tier | E1: Total Lost Sales ($) | F1: Total Units Sold | G1: Avg Stockout Days/Month | H1: Avg Inventory Turns
A2: BED-201 | B2: Cooling Bamboo Sheet Set | C2: Bedding | D2: fast | E2: =SUMIF('Raw Data'!$C$2:$C$241,A2,'Raw Data'!$L$2:$L$241) -> 122958 | F2: =SUMIF('Raw Data'!$C$2:$C$241,A2,'Raw Data'!$K$2:$K$241) -> 5585 | G2: =ROUND(AVERAGEIF('Raw Data'!$C$2:$C$241,A2,'Raw Data'!$I$2:$I$241),1) -> 8.2 | H2: =ROUND(AVERAGEIF('Raw Data'!$C$2:$C$241,A2,'Raw Data'!$N$2:$N$241),2) -> 9.67
A3: OUT-501 | B3: Folding Patio Chair | C3: Outdoor | D3: fast | E3: =SUMIF('Raw Data'!$C$2:$C$241,A3,'Raw Data'!$L$2:$L$241) -> 108168.5 | F3: =SUMIF('Raw Data'!$C$2:$C$241,A3,'Raw Data'!$K$2:$K$241) -> 5835 | G3: =ROUND(AVERAGEIF('Raw Data'!$C$2:$C$241,A3,'Raw Data'!$I$2:$I$241),1) -> 7.8 | H3: =ROUND(AVERAGEIF('Raw Data'!$C$2:$C$241,A3,'Raw Data'!$N$2:$N$241),2) -> 9.7
A4: KIT-101 | B4: Ceramic Nonstick Pan Set | C4: Kitchen | D4: fast | E4: =SUMIF('Raw Data'!$C$2:$C$241,A4,'Raw Data'!$L$2:$L$241) -> 86413.5 | F4: =SUMIF('Raw Data'!$C$2:$C$241,A4,'Raw Data'!$K$2:$K$241) -> 5798 | G4: =ROUND(AVERAGEIF('Raw Data'!$C$2:$C$241,A4,'Raw Data'!$I$2:$I$241),1) -> 7.5 | H4: =ROUND(AVERAGEIF('Raw Data'!$C$2:$C$241,A4,'Raw Data'!$N$2:$N$241),2) -> 9.98
A5: DEC-401 | B5: Scented Soy Candle 3-Pack | C5: Decor | D5: fast | E5: =SUMIF('Raw Data'!$C$2:$C$241,A5,'Raw Data'!$L$2:$L$241) -> 65060.8 | F5: =SUMIF('Raw Data'!$C$2:$C$241,A5,'Raw Data'!$K$2:$K$241) -> 5569 | G5: =ROUND(AVERAGEIF('Raw Data'!$C$2:$C$241,A5,'Raw Data'!$I$2:$I$241),1) -> 9.1 | H5: =ROUND(AVERAGEIF('Raw Data'!$C$2:$C$241,A5,'Raw Data'!$N$2:$N$241),2) -> 8.48
A6: STO-301 | B6: Stackable Closet Bins | C6: Storage | D6: fast | E6: =SUMIF('Raw Data'!$C$2:$C$241,A6,'Raw Data'!$L$2:$L$241) -> 51875 | F6: =SUMIF('Raw Data'!$C$2:$C$241,A6,'Raw Data'!$K$2:$K$241) -> 5645 | G6: =ROUND(AVERAGEIF('Raw Data'!$C$2:$C$241,A6,'Raw Data'!$I$2:$I$241),1) -> 7.9 | H6: =ROUND(AVERAGEIF('Raw Data'!$C$2:$C$241,A6,'Raw Data'!$N$2:$N$241),2) -> 9.57
A7: DEC-402 | B7: Wall Art Canvas Print | C7: Decor | D7: slow | E7: =SUMIF('Raw Data'!$C$2:$C$241,A7,'Raw Data'!$L$2:$L$241) -> 2695 | F7: =SUMIF('Raw Data'!$C$2:$C$241,A7,'Raw Data'!$K$2:$K$241) -> 2202 | G7: =ROUND(AVERAGEIF('Raw Data'!$C$2:$C$241,A7,'Raw Data'!$I$2:$I$241),1) -> 0.9 | H7: =ROUND(AVERAGEIF('Raw Data'!$C$2:$C$241,A7,'Raw Data'!$N$2:$N$241),2) -> 1.03
A8: KIT-102 | B8: Glass Storage Container Set | C8: Kitchen | D8: slow | E8: =SUMIF('Raw Data'!$C$2:$C$241,A8,'Raw Data'!$L$2:$L$241) -> 1947 | F8: =SUMIF('Raw Data'!$C$2:$C$241,A8,'Raw Data'!$K$2:$K$241) -> 2417 | G8: =ROUND(AVERAGEIF('Raw Data'!$C$2:$C$241,A8,'Raw Data'!$I$2:$I$241),1) -> 1.1 | H8: =ROUND(AVERAGEIF('Raw Data'!$C$2:$C$241,A8,'Raw Data'!$N$2:$N$241),2) -> 1.07
A9: STO-302 | B9: Under-Bed Storage Box | C9: Storage | D9: slow | E9: =SUMIF('Raw Data'!$C$2:$C$241,A9,'Raw Data'!$L$2:$L$241) -> 1804 | F9: =SUMIF('Raw Data'!$C$2:$C$241,A9,'Raw Data'!$K$2:$K$241) -> 2664 | G9: =ROUND(AVERAGEIF('Raw Data'!$C$2:$C$241,A9,'Raw Data'!$I$2:$I$241),1) -> 1 | H9: =ROUND(AVERAGEIF('Raw Data'!$C$2:$C$241,A9,'Raw Data'!$N$2:$N$241),2) -> 1.22
A10: BED-202 | B10: Decorative Throw Pillow | C10: Bedding | D10: slow | E10: =SUMIF('Raw Data'!$C$2:$C$241,A10,'Raw Data'!$L$2:$L$241) -> 1485 | F10: =SUMIF('Raw Data'!$C$2:$C$241,A10,'Raw Data'!$K$2:$K$241) -> 2633 | G10: =ROUND(AVERAGEIF('Raw Data'!$C$2:$C$241,A10,'Raw Data'!$I$2:$I$241),1) -> 0.9 | H10: =ROUND(AVERAGEIF('Raw Data'!$C$2:$C$241,A10,'Raw Data'!$N$2:$N$241),2) -> 1.16
A11: OUT-502 | B11: Garden Planter Pot | C11: Outdoor | D11: slow | E11: =SUMIF('Raw Data'!$C$2:$C$241,A11,'Raw Data'!$L$2:$L$241) -> 1162.5 | F11: =SUMIF('Raw Data'!$C$2:$C$241,A11,'Raw Data'!$K$2:$K$241) -> 2235 | G11: =ROUND(AVERAGEIF('Raw Data'!$C$2:$C$241,A11,'Raw Data'!$I$2:$I$241),1) -> 1 | H11: =ROUND(AVERAGEIF('Raw Data'!$C$2:$C$241,A11,'Raw Data'!$N$2:$N$241),2) -> 1.11

Sheet Store Summary
A1: Store | B1: Total Lost Sales ($) | C1: Total Units Sold
A2: Downtown | B2: =SUMIF('Raw Data'!$B$2:$B$241,A2,'Raw Data'!$L$2:$L$241) -> 141511.2 | C2: =SUMIF('Raw Data'!$B$2:$B$241,A2,'Raw Data'!$K$2:$K$241) -> 12291
A3: Suburb | B3: =SUMIF('Raw Data'!$B$2:$B$241,A3,'Raw Data'!$L$2:$L$241) -> 114182 | C3: =SUMIF('Raw Data'!$B$2:$B$241,A3,'Raw Data'!$K$2:$K$241) -> 9144
A4: Uptown | B4: =SUMIF('Raw Data'!$B$2:$B$241,A4,'Raw Data'!$L$2:$L$241) -> 95711.7 | C4: =SUMIF('Raw Data'!$B$2:$B$241,A4,'Raw Data'!$K$2:$K$241) -> 10853
A5: Riverside | B5: =SUMIF('Raw Data'!$B$2:$B$241,A5,'Raw Data'!$L$2:$L$241) -> 92164.4 | C5: =SUMIF('Raw Data'!$B$2:$B$241,A5,'Raw Data'!$K$2:$K$241) -> 8295

Sheet Month Summary
A1: Month | B1: Total Lost Sales ($)
A2: 2026-01 | B2: =SUMIF('Raw Data'!$A$2:$A$241,A2,'Raw Data'!$L$2:$L$241) -> 77942.3
A3: 2026-02 | B3: =SUMIF('Raw Data'!$A$2:$A$241,A3,'Raw Data'!$L$2:$L$241) -> 74741.6
A4: 2026-03 | B4: =SUMIF('Raw Data'!$A$2:$A$241,A4,'Raw Data'!$L$2:$L$241) -> 72658.7
A5: 2026-04 | B5: =SUMIF('Raw Data'!$A$2:$A$241,A5,'Raw Data'!$L$2:$L$241) -> 72906.5
A6: 2026-05 | B6: =SUMIF('Raw Data'!$A$2:$A$241,A6,'Raw Data'!$L$2:$L$241) -> 66454.1
A7: 2026-06 | B7: =SUMIF('Raw Data'!$A$2:$A$241,A7,'Raw Data'!$L$2:$L$241) -> 78866.1
A9: 6-Month Total | B9: =SUM(B2:B7) -> 443569.3
A10: Annualized Estimate (6-mo sample x2) | B10: =B9*2 -> 887138.6

Sheet Dashboard
A1: Inventory Stockout & Overstock Analytics — Meridian Home Goods
A2: 6-month sample, Jan–Jun 2026, across 4 stores and 10 SKUs
K4: Key Metrics
K22: Total Lost Sales (6-mo sample) | M22: ='Month Summary'!B9 -> 443569.3
K23: Annualized Lost Sales Estimate | M23: ='Month Summary'!B10 -> 887138.6
K24: Fast-Mover Avg Inventory Turns | M24: =ROUND(AVERAGEIF('Raw Data'!O2:O241,"fast",'Raw Data'!N2:N241),2) -> 9.48
K25: Slow-Mover Avg Inventory Turns | M25: =ROUND(AVERAGEIF('Raw Data'!O2:O241,"slow",'Raw Data'!N2:N241),2) -> 1.12

Sheet Assumptions & Notes
A1: Assumptions & Notes
A3: 1. Data source: Synthetic dataset constructed for this portfolio case study — not real company data.
A4: 2. Sample window: 6 months (Jan–Jun 2026), 4 stores, 10 SKUs across 5 categories (2 SKUs per category).
A5: 3. Demand assumption: when a SKU is in stock, 100% of average daily demand is assumed sold (no substitution modeled).
A6: 4. Lost Sales ($) = Days Out of Stock x Avg Daily Demand x Unit Price — this values forgone revenue at full retail
A7: price during stockout days; it is not margin-adjusted.
A8: 5. Inventory Turns = Units Sold / Avg Inventory (units) for the sample period — a simplified proxy, not an annualized
A9: turns ratio.
A10: 6. Annualized Lost Sales Estimate = 6-month sample total x 2, shown on the Month Summary and Dashboard tabs.
A11: This is a straight-line extrapolation and does not account for seasonality.
A12: 7. 'Fast' tier = the 5 highest-demand SKUs (one per category); 'Slow' tier = the 5 lowest-demand SKUs (one per
A13: category) — assigned by design to illustrate the stockout-vs-overstock pattern described in the Business Case.
... A16: workbook, but reproducible from the 'Avg Inventory (units)' and 'Unit Price' columns on Raw Data.
